ai4u_ml/__init__.py
ai4u_ml/sb3_sac_mi_trainer.py
ai4u_ml/sb3_sac_mlp_trainer.py
ai4u_ml/sb3_sac_runner.py
ai4u_ml/sb3_sac_trainer.py
ai4u_ml-0.5.0.dist-info/METADATA
ai4u_ml-0.5.0.dist-info/WHEEL
ai4u_ml-0.5.0.dist-info/top_level.txt
ai4u_ml-0.5.0.dist-info/RECORD
