Metadata-Version: 2.4
Name: ai4u_ml
Version: 0.5.0
Summary: AI4U ML install ml prerequisites for AI4U framework
Author: Gilzamir Gomes
Classifier: Programming Language :: Python :: 3.10
Classifier: License :: OSI Approved :: MIT License
Classifier: Operating System :: OS Independent
Requires-Python: >=3.10
Requires-Dist: numpy==1.26.4
Requires-Dist: gymnasium==0.29.1
Requires-Dist: stable-baselines3==2.3.2
Requires-Dist: torch==2.7.0
Requires-Dist: tensorboard==2.16.2
Requires-Dist: shimmy==1.3.0
Dynamic: author
Dynamic: classifier
Dynamic: description
Dynamic: description-content-type
Dynamic: requires-dist
Dynamic: requires-python
Dynamic: summary
